sphinx_collections-0.0.1-py3.8-nspkg.pth
sphinxcontrib/collections/__init__.py
sphinxcontrib/collections/api.py
sphinxcontrib/collections/collections.py
sphinxcontrib/collections/main.py
sphinxcontrib/collections/directives/__init__.py
sphinxcontrib/collections/directives/if_collection.py
sphinxcontrib/collections/drivers/__init__.py
sphinxcontrib/collections/drivers/copy.py
sphinxcontrib/collections/drivers/copy_file.py
sphinxcontrib/collections/drivers/copy_folder.py
sphinxcontrib/collections/drivers/function.py
sphinxcontrib/collections/drivers/git.py
sphinxcontrib/collections/drivers/jinja.py
sphinxcontrib/collections/drivers/report.py
sphinxcontrib/collections/drivers/report.rst.template
sphinxcontrib/collections/drivers/string.py
sphinxcontrib/collections/drivers/symlink.py
sphinx_collections-0.0.1.dist-info/LICENSE
sphinx_collections-0.0.1.dist-info/METADATA
sphinx_collections-0.0.1.dist-info/WHEEL
sphinx_collections-0.0.1.dist-info/namespace_packages.txt
sphinx_collections-0.0.1.dist-info/top_level.txt
sphinx_collections-0.0.1.dist-info/RECORD
