Metadata-Version: 2.1
Name: sphinx-collections
Version: 0.0.1
Summary: Sphinx extension for collecting external data for Sphinx build.
Home-page: http://github.com/useblocks/sphinx-collections
Author: team useblocks
Author-email: info@useblocks.com
License: MIT
Download-URL: http://pypi.python.org/pypi/sphinx-collections
Platform: any
Classifier: Development Status :: 4 - Beta
Classifier: Intended Audience :: Developers
Classifier: License :: OSI Approved :: MIT License
Classifier: Operating System :: OS Independent
Classifier: Programming Language :: Python
Classifier: Programming Language :: Python :: 3
Classifier: Programming Language :: Python :: 3.5
Classifier: Programming Language :: Python :: 3.6
Classifier: Programming Language :: Python :: 3.7
Classifier: Topic :: Documentation
Classifier: Topic :: Utilities
Requires-Dist: sphinx (>2.0)
Requires-Dist: jinja2
Requires-Dist: gitpython
